{"cameraMode":{"drawMode":0,"name":"Shaded","section":"Shading Mode"},"sceneLighting":true,"audioPlay":false,"sceneViewState":{"m_AlwaysRefresh":false,"showFog":true,"showSkybox":true,"showFlares":true,"showImageEffects":true,"showParticleSystems":true,"showVisualEffectGraphs":true,"m_FxEnabled":true},"in2DMode":false,"pivot":{"x":0.5940130949020386,"y":-6.179866790771484,"z":4.14976692199707},"rotation":{"x":-0.35527998208999636,"y":0.36756643652915957,"z":-0.1544567197561264,"w":-0.8454737067222595},"size":10.063170433044434,"orthographic":false}